setup.py
prosodypy/__init__.py
prosodypy/__main__.py
prosodypy/auth.py
prosodypy/base.py
prosodypy/decorators.py
prosodypy/django_compat.py
prosodypy.egg-info/PKG-INFO
prosodypy.egg-info/SOURCES.txt
prosodypy.egg-info/dependency_links.txt
prosodypy.egg-info/top_level.txt
prosodypy/examples/__init__.py
prosodypy/examples/mod_auth_pyanonymous.py
prosodypy/examples/mod_hello_world.py
prosodypy/mod_prosodypy/mod_prosodypy.lua
prosodypy/twilix_compat/__init__.py
prosodypy/twilix_compat/element.py