Metadata-Version: 1.0
Name: prosodypy
Version: 0.2
Summary: A compatibility suite to write modules in Python for ProsodyXMPP Server
Home-page: https://github.com/jbinary/prosodypy
Author: Sergey Dobrov
Author-email: binary@jrudevels.org
License: UNKNOWN
Platform: UNKNOWN
